pyala/__init__.py
pyala/pyala.py
pyala-0.1.0.dist-info/LICENSE
pyala-0.1.0.dist-info/METADATA
pyala-0.1.0.dist-info/WHEEL
pyala-0.1.0.dist-info/RECORD
