Metadata-Version: 2.1
Name: pyala
Version: 0.1.0
Summary: 
Author: Ludovic Trottier
Author-email: ludovic.trottier.1@gmail.com
Requires-Python: >=3.8.1,<4.0
Classifier: Programming Language :: Python :: 3
Classifier: Programming Language :: Python :: 3.9
Classifier: Programming Language :: Python :: 3.10
Classifier: Programming Language :: Python :: 3.11
Requires-Dist: parse (>=1.19.0,<2.0.0)
